conturtle/__init__.py
conturtle/main.py
conturtle-0.0.8.dist-info/METADATA
conturtle-0.0.8.dist-info/WHEEL
conturtle-0.0.8.dist-info/top_level.txt
conturtle-0.0.8.dist-info/RECORD
