Metadata-Version: 2.1
Name: conturtle
Version: 0.0.8
Summary: a console version of python turtle
Home-page: https://github.com/LogSkele/conturtle
Author: iop3
Author-email: keystove@gmail.com
Project-URL: Bug Tracker, https://github.com/LogSkele/conturtle/issues
Classifier: Programming Language :: Python :: 3
Classifier: License :: OSI Approved :: MIT License
Classifier: Operating System :: OS Independent
Requires-Python: >=3.6
